tfgen/__init__.py
tfgen/cli.py
tfgen/terraform_parser.py
tfgen/ui.py
el_tfgen-0.2.6.dist-info/METADATA
el_tfgen-0.2.6.dist-info/WHEEL
el_tfgen-0.2.6.dist-info/entry_points.txt
el_tfgen-0.2.6.dist-info/top_level.txt
el_tfgen-0.2.6.dist-info/RECORD
