Metadata-Version: 2.4
Name: eL-tfgen
Version: 0.2.6
Summary: AI-powered Terraform module generator - Create Terraform configurations from provider documentation
Author: eLTitans
License: MIT
Keywords: terraform,ai,code-generation,infrastructure-as-code,automation,claude
Classifier: Development Status :: 4 - Beta
Classifier: Intended Audience :: Developers
Classifier: Intended Audience :: System Administrators
Classifier: Topic :: Software Development :: Code Generators
Classifier: Topic :: System :: Systems Administration
Classifier: License :: OSI Approved :: MIT License
Classifier: Programming Language :: Python :: 3
Classifier: Programming Language :: Python :: 3.8
Classifier: Programming Language :: Python :: 3.9
Classifier: Programming Language :: Python :: 3.10
Classifier: Programming Language :: Python :: 3.11
Classifier: Programming Language :: Python :: 3.12
Classifier: Programming Language :: Python :: 3.13
Requires-Python: >=3.8
Requires-Dist: playwright
Requires-Dist: beautifulsoup4
Requires-Dist: anthropic
Requires-Dist: python-dotenv
Requires-Dist: Pillow
Requires-Dist: customtkinter
Dynamic: requires-python
